tests/__init__.py
tests/test_db.py
tests/test_main.py
tests/test_streamlit.py
tests/test_task.py
tests/test_task_manager.py
to_do_list/__init__.py
to_do_list/db.py
to_do_list/main.py
to_do_list/streamlit_app.py
to_do_list/task.py
to_do_list/task_manager.py
to_do_list_project/__init__.py
to_do_list_project/db.py
to_do_list_project/main.py
to_do_list_project/streamlit_app.py
to_do_list_project/task.py
to_do_list_project/task_manager.py
Kit_Big_Data_To_Do_List-1.3.dist-info/METADATA
Kit_Big_Data_To_Do_List-1.3.dist-info/WHEEL
Kit_Big_Data_To_Do_List-1.3.dist-info/top_level.txt
Kit_Big_Data_To_Do_List-1.3.dist-info/RECORD
