Metadata-Version: 2.1
Name: Kit-Big-Data-To-Do-List
Version: 1.3
Summary: To Do List helps you manage your agenda by creating a list of your tasks
Home-page: https://github.com/jaimeMontea/Kit_BIG_Data
Author: Florent BRIAND, Maxime LEDIEU Jaime MONTEA, Edouard DUCLOY, Pierre BILLAUD
Author-email: florent.briand56@gmail.com
Requires-Python: >=3.10
Requires-Dist: numpy (>=1.18.0)
Requires-Dist: altair (==5.1.2)
Requires-Dist: attrs (==23.1.0)
Requires-Dist: blinker (==1.6.3)
Requires-Dist: build (==0.10.0)
Requires-Dist: CacheControl (==0.13.1)
Requires-Dist: cachetools (==5.3.1)
Requires-Dist: certifi (==2023.7.22)
Requires-Dist: charset-normalizer (==3.3.0)
Requires-Dist: cleo (==2.0.1)
Requires-Dist: click (==8.1.7)
Requires-Dist: colorama (==0.4.6)
Requires-Dist: crashtest (==0.4.1)
Requires-Dist: distlib (==0.3.7)
Requires-Dist: dulwich (==0.21.6)
Requires-Dist: filelock (==3.12.4)
Requires-Dist: gitdb (==4.0.10)
Requires-Dist: GitPython (==3.1.40)
Requires-Dist: idna (==3.4)
Requires-Dist: importlib-metadata (==6.8.0)
Requires-Dist: installer (==0.7.0)
Requires-Dist: jaraco.classes (==3.3.0)
Requires-Dist: Jinja2 (==3.1.2)
Requires-Dist: jsonschema (==4.17.3)
Requires-Dist: jsonschema-specifications (==2023.7.1)
Requires-Dist: keyring (==24.2.0)
Requires-Dist: markdown-it-py (==3.0.0)
Requires-Dist: MarkupSafe (==2.1.3)
Requires-Dist: mdurl (==0.1.2)
Requires-Dist: more-itertools (==10.1.0)
Requires-Dist: msgpack (==1.0.7)
Requires-Dist: numpy (==1.25.2)
Requires-Dist: packaging (==23.2)
Requires-Dist: pexpect (==4.8.0)
Requires-Dist: Pillow (==10.1.0)
Requires-Dist: pkginfo (==1.9.6)
Requires-Dist: platformdirs (==3.11.0)
Requires-Dist: poetry (==1.6.1)
Requires-Dist: poetry-core (==1.7.0)
Requires-Dist: poetry-plugin-export (==1.5.0)
Requires-Dist: protobuf (==4.24.4)
Requires-Dist: ptyprocess (==0.7.0)
Requires-Dist: pyarrow (==13.0.0)
Requires-Dist: pydeck (==0.8.1b0)
Requires-Dist: Pygments (==2.16.1)
Requires-Dist: pyproject-hooks (==1.0.0)
Requires-Dist: pyrsistent (==0.19.3)
Requires-Dist: python-dateutil (==2.8.2)
Requires-Dist: pytz (==2023.3.post1)
Requires-Dist: pywin32-ctypes (==0.2.2)
Requires-Dist: rapidfuzz (==2.15.2)
Requires-Dist: referencing (==0.30.2)
Requires-Dist: requests (==2.31.0)
Requires-Dist: requests-toolbelt (==1.0.0)
Requires-Dist: rich (==13.6.0)
Requires-Dist: rpds-py (==0.10.6)
Requires-Dist: shellingham (==1.5.4)
Requires-Dist: six (==1.16.0)
Requires-Dist: smmap (==5.0.1)
Requires-Dist: tenacity (==8.2.3)
Requires-Dist: toml (==0.10.2)
Requires-Dist: tomlkit (==0.12.1)
Requires-Dist: toolz (==0.12.0)
Requires-Dist: tornado (==6.3.3)
Requires-Dist: trove-classifiers (==2023.10.18)
Requires-Dist: typing-extensions (==4.8.0)
Requires-Dist: tzdata (==2023.3)
Requires-Dist: tzlocal (==5.1)
Requires-Dist: urllib3 (==2.0.7)
Requires-Dist: validators (==0.22.0)
Requires-Dist: virtualenv (==20.24.6)
Requires-Dist: watchdog (==3.0.0)
Requires-Dist: zipp (==3.17.0)
